Py3DFreeHandUS/LICENSE.txt
Py3DFreeHandUS/__init__.py
Py3DFreeHandUS/array_helpers.py
Py3DFreeHandUS/benchmark_calib_c.py
Py3DFreeHandUS/benchmark_image_utils_c.py
Py3DFreeHandUS/calib.py
Py3DFreeHandUS/calib_c.cp37-win_amd64.pyd
Py3DFreeHandUS/calib_c.pyx
Py3DFreeHandUS/converters.py
Py3DFreeHandUS/cython_setup.py
Py3DFreeHandUS/image_utils.py
Py3DFreeHandUS/image_utils_c.cp37-win_amd64.pyd
Py3DFreeHandUS/image_utils_c.pxd
Py3DFreeHandUS/image_utils_c.pyx
Py3DFreeHandUS/kine.py
Py3DFreeHandUS/math_utils.py
Py3DFreeHandUS/muscles_analysis.py
Py3DFreeHandUS/particle_filter.py
Py3DFreeHandUS/process.py
Py3DFreeHandUS/pyver.py
Py3DFreeHandUS/segment.py
Py3DFreeHandUS/test_image_utils_c.py
Py3DFreeHandUS/test_voxel_filling_methods.py
Py3DFreeHandUS/tracking.py
Py3DFreeHandUS/voxel_array_utils.py
Py3DFreeHandUS-1.0.0.dist-info/METADATA
Py3DFreeHandUS-1.0.0.dist-info/WHEEL
Py3DFreeHandUS-1.0.0.dist-info/top_level.txt
Py3DFreeHandUS-1.0.0.dist-info/RECORD
